Metadata-Version: 1.0
Name: prime-algorithms
Version: 1.0
Summary: Prime algorithms
Home-page: UNKNOWN
Author: KATHURIA Pulkit
Author-email: kevincobain2000@gmail.com
License: LICENSE.txt
Platform: UNKNOWN
